hexagonal/__init__.py
hexagonal/py.typed
hexagonal-0.0.3.dist-info/LICENSE
hexagonal-0.0.3.dist-info/WHEEL
hexagonal-0.0.3.dist-info/METADATA
hexagonal-0.0.3.dist-info/RECORD
