Metadata-Version: 2.1
Name: hexagonal
Version: 0.0.3
Summary: Hexagonal provides hexagonal vectors.
Author: Tom Fryers
Requires-Python: >=3.9
Classifier: Development Status :: 3 - Alpha
Classifier: Programming Language :: Python :: 3
Classifier: License :: OSI Approved :: GNU General Public License v3 or later (GPLv3+)
Classifier: Operating System :: OS Independent
Project-URL: Home, https://gitlab.com/Tom_Fryers/hexagonal
